<?xml version="1.0" encoding="UTF-8"?>
<?xml-model href="schema0.xsd" type="application/xml" schematypens="http://www.w3.org/2001/XMLSchema"?>
<GameConfig>
    <InkStory>EG1-1</InkStory>
    <player>
        <personality></personality>
        <max_card_num>10</max_card_num>
        <draw_num>4</draw_num>
        <max_pressure>10</max_pressure>
        <max_health>10</max_health>
        <everry_turn_energy>2</everry_turn_energy>
        <cards>
            <string>distribution</string>
            <string>distribution</string>
            <string>distribution</string>
            <string>standpoint</string>
            <string>standpoint</string>
            <string>adjested_ideas</string>
            <string>tipsy</string>
            <string>tipsy</string>
            <string>tipsy</string>
            <string>excited</string>
            <string>tear</string>
            <string>tear</string>
            <string>sound_out</string>
        </cards>
    </player>
    <enemy>
        
    </enemy>
</GameConfig>